{
	"animations": [
		{
			"loop": false,
			"offsets": [-6, -5],
			"anim": "danceLeft",
			"fps": 24,
			"name": "girl idel assist",
			"indices": [0, 1, 2, 3, 4, 5, 6, 7, 8, 9, 10, 11, 12, 13]
		},
		{
			"loop": false,
			"offsets": [-6, -5],
			"anim": "danceRight",
			"fps": 24,
			"name": "girl idel assist",
			"indices": [14, 15, 16, 17, 18, 19, 20, 21, 22, 23, 24, 25, 26, 27]
		},
		{
			"offsets": [60, -13],
			"loop": false,
			"fps": 24,
			"anim": "singLEFT",
			"indices": [],
			"name": "girl left"
		},
		{
			"offsets": [-25, -47],
			"loop": false,
			"fps": 24,
			"anim": "singDOWN",
			"indices": [],
			"name": "girl goin down"
		},
		{
			"offsets": [-25, 40],
			"loop": false,
			"fps": 24,
			"anim": "singUP",
			"indices": [],
			"name": "girl le up pose"
		},
		{
			"offsets": [-30, -28],
			"loop": false,
			"fps": 24,
			"anim": "singRIGHT",
			"indices": [],
			"name": "girl rihgt turn"
		},
		{
			"offsets": [64, 10],
			"loop": false,
			"fps": 24,
			"anim": "singLEFTmiss",
			"indices": [],
			"name": "girl missed left"
		},
		{
			"offsets": [-25, -25],
			"loop": false,
			"fps": 24,
			"anim": "singDOWNmiss",
			"indices": [],
			"name": "girl uh oh down"
		},
		{
			"offsets": [-33, 63],
			"loop": false,
			"fps": 24,
			"anim": "singUPmiss",
			"indices": [],
			"name": "girl el miss up"
		},
		{
			"offsets": [-30, -3],
			"loop": false,
			"fps": 24,
			"anim": "singRIGHTmiss",
			"indices": [],
			"name": "girl missed turn"
		},
		{
			"loop": false,
			"offsets": [-6, -5],
			"anim": "danceLeft-alt",
			"fps": 24,
			"name": "girl idel le alte",
			"indices": [0, 1, 2, 3, 4, 5, 6, 7, 8, 9, 10, 11, 12, 13]
		},
		{
			"loop": false,
			"offsets": [-6, -5],
			"anim": "danceRight-alt",
			"fps": 24,
			"name": "girl idel le alte",
			"indices": [14, 15, 16, 17, 18, 19, 20, 21, 22, 23, 24, 25, 26, 27]
		},
		{
			"offsets": [-17, 0],
			"loop": false,
			"fps": 24,
			"anim": "what",
			"indices": [],
			"name": "girl what"
		},
		{
			"offsets": [-11, 27],
			"indices": [],
			"fps": 1,
			"anim": "hey",
			"loop": false,
			"name": "girl eyah ppose"
		}
	],
	"vocals_file": "",
	"no_antialiasing": false,
	"image": "characters/truckergirl",
	"position": [190, 40],
	"healthicon": "truckgirl",
	"flip_x": false,
	"healthbar_colors": [197, 82, 82],
	"camera_position": [-170, -80],
	"sing_duration": 4,
	"scale": 1,
	"_editor_isPlayer": false
}